setup.cfg
setup.py
fastqc_to_json/__init__.py
fastqc_to_json/__main__.py
fastqc_to_json/main.py
fastqc_to_json.egg-info/PKG-INFO
fastqc_to_json.egg-info/SOURCES.txt
fastqc_to_json.egg-info/dependency_links.txt
fastqc_to_json.egg-info/entry_points.txt
fastqc_to_json.egg-info/top_level.txt