Metadata-Version: 1.1
Name: fastqc-to-json
Version: 0.4
Summary: fastqc to json for bwa cwl
Home-page: https://github.com/jeremiahsavage/fastqc_to_json
Author: Jeremiah H. Savage
Author-email: jeremiahsavage@gmail.com
License: Apache 2.0
Platform: UNKNOWN
Classifier: Development Status :: 3 - Alpha
Classifier: Intended Audience :: Developers
Classifier: License :: OSI Approved :: Apache Software License
Classifier: Programming Language :: Python
Classifier: Programming Language :: Python :: 2
Classifier: Programming Language :: Python :: 3
